molvizr3d/__init__.py
molvizr3d/app.py
molvizr3d/config/__init__.py
molvizr3d/config/constants.py
molvizr3d/config/setting.py
molvizr3d/data/__init__.py
molvizr3d/docs/__init__.py
molvizr3d/docs/compound.py
molvizr3d/docs/compute.py
molvizr3d/docs/element.py
molvizr3d/docs/molparser.py
molvizr3d/docs/observer.py
molvizr3d/docs/structure.py
molvizr3d/docs/utility.py
molvizr3d/docs/vizr3d.py
MolVizr3D-1.0.0.dist-info/LICENSE
MolVizr3D-1.0.0.dist-info/METADATA
MolVizr3D-1.0.0.dist-info/WHEEL
MolVizr3D-1.0.0.dist-info/top_level.txt
MolVizr3D-1.0.0.dist-info/RECORD
