Metadata-Version: 2.1
Name: MolVizr3D
Version: 1.0.0
Summary: MolVizr3D: Molecular Visualizer in 3D.
Author: Sina Gilassi
Author-email: <sina.gilassi@gmail.com>
License: MIT
Keywords: python,chemistry,chemistry-visualization,MolVizr3D
Classifier: Development Status :: 1 - Planning
Classifier: Intended Audience :: Education
Classifier: Programming Language :: Python :: 3
Classifier: Operating System :: Unix
Classifier: Operating System :: MacOS :: MacOS X
Classifier: Operating System :: Microsoft :: Windows
Requires-Python: >=3.6
License-File: LICENSE
Requires-Dist: pandas
Requires-Dist: pillow
Requires-Dist: requests
Requires-Dist: urllib3
Requires-Dist: matplotlib
Requires-Dist: PubChemQuery
Requires-Dist: numpy
